flask_setup/__init__.py
flask_setup/decorators.py
flask_setup/methods.py
flask_setup/commands/__init__.py
flask_setup/commands/add.py
flask_setup/commands/build.py
flask_setup/commands/install.py
flask_setup/commands/remove.py
flask_setup/commands/start.py
flask_setup/commands/uninstall.py
flask_setup/generators/blueprint/controller.py
flask_setup/generators/blueprint/model.py
flask_setup/generators/blueprint/schema.py
flask_setup/generators/samples/sample.model.py
flask_setup/generators/samples/sample.schema.py
flask_setup/generators/samples/user.model.py
flask_setup/starter/.env
flask_setup/starter/.fs
flask_setup/starter/Dockerfile
flask_setup/starter/README.md
flask_setup/starter/main.py
flask_setup/starter/manage.py
flask_setup/starter/run
flask_setup/starter/supervisord.conf
flask_setup/starter/app/__init__.py
flask_setup/starter/app/error_handlers.py
flask_setup/starter/app/route_guard.py
flask_setup/starter/app/celery/__init__.py
flask_setup/starter/app/celery/tasks.py
flask_setup/starter/app/user/controller.py
flask_setup/starter/app/user/model.py
flask_setup/starter/app/user/schema.py
flask_setup/starter/config/__init__.py
flask_setup/starter/config/celery.py
flask_setup/starter/config/db.py
flask_setup/starter/config/jwt.py
flask_setup/starter/config/mail.py
flask_setup/starter/helpers/__init__.py
flask_setup-0.7.8.1.data/data/generators/controller.py
flask_setup-0.7.8.1.data/data/generators/model.py
flask_setup-0.7.8.1.data/data/generators/sample.model.py
flask_setup-0.7.8.1.data/data/generators/sample.schema.py
flask_setup-0.7.8.1.data/data/generators/schema.py
flask_setup-0.7.8.1.data/data/generators/user.model.py
flask_setup-0.7.8.1.data/data/starter/.env
flask_setup-0.7.8.1.data/data/starter/Dockerfile
flask_setup-0.7.8.1.data/data/starter/README.md
flask_setup-0.7.8.1.data/data/starter/__init__.py
flask_setup-0.7.8.1.data/data/starter/celery.py
flask_setup-0.7.8.1.data/data/starter/controller.py
flask_setup-0.7.8.1.data/data/starter/db.py
flask_setup-0.7.8.1.dist-info/METADATA
flask_setup-0.7.8.1.dist-info/WHEEL
flask_setup-0.7.8.1.dist-info/entry_points.txt
flask_setup-0.7.8.1.dist-info/top_level.txt
flask_setup-0.7.8.1.dist-info/RECORD
