Metadata-Version: 2.1
Name: flask-setup
Version: 0.7.8.1
Summary: A simple tool to help you setup a flask project quickly
Home-page: https://github.com/mrteey/flask-setup
Author: Nasir Mustapha
Author-email: nasir@mrteey.com
License: UNKNOWN
Platform: UNKNOWN
Classifier: Programming Language :: Python :: 3
Classifier: License :: OSI Approved :: MIT License
Classifier: Operating System :: OS Independent
Requires-Dist: typer
Requires-Dist: rich>=10.0.0
Requires-Dist: typing-extensions>=4.0.0
